app/__init__.py
app/auth/__init__.py
app/auth/adapter/__init__.py
app/auth/adapter/input/__init__.py
app/auth/adapter/input/api/__init__.py
app/auth/adapter/input/api/v1/__init__.py
app/auth/adapter/input/api/v1/auth.py
app/auth/adapter/input/api/v1/request/__init__.py
app/auth/adapter/input/api/v1/response/__init__.py
app/auth/application/__init__.py
app/auth/application/dto/__init__.py
app/auth/application/exception/__init__.py
app/auth/application/service/__init__.py
app/auth/application/service/jwt.py
app/auth/domain/__init__.py
app/auth/domain/entity/__init__.py
app/auth/domain/usecase/__init__.py
app/auth/domain/usecase/jwt.py
app/container.py
app/main.py
app/openfund/__init__.py
app/openfund/adapter/__init__.py
app/openfund/adapter/input/__init__.py
app/openfund/adapter/input/api/__init__.py
app/openfund/adapter/input/api/v1/__init__.py
app/openfund/adapter/input/api/v1/collect_api.py
app/openfund/adapter/input/api/v1/request/__init__.py
app/openfund/adapter/input/api/v1/response/__init__.py
app/openfund/adapter/output/__init__.py
app/openfund/application/__init__.py
app/openfund/application/dto/__init__.py
app/openfund/application/exception/__init__.py
app/openfund/application/service/__init__.py
app/openfund/application/service/collect_service.py
app/openfund/container.py
app/openfund/domain/__init__.py
app/openfund/domain/entity/__init__.py
app/openfund/domain/entity/um_futures_collector.py
app/openfund/domain/usecase/__init__.py
app/openfund/domain/usecase/collect_usecase.py
app/server.py
app/user/__init__.py
app/user/adapter/__init__.py
app/user/adapter/input/__init__.py
app/user/adapter/input/api/__init__.py
app/user/adapter/input/api/v1/__init__.py
app/user/adapter/input/api/v1/request/__init__.py
app/user/adapter/input/api/v1/response/__init__.py
app/user/adapter/input/api/v1/user.py
app/user/adapter/output/__init__.py
app/user/adapter/output/persistence/__init__.py
app/user/adapter/output/persistence/repository_adapter.py
openfund_server-0.4.3.dist-info/LICENSE
openfund_server-0.4.3.dist-info/METADATA
openfund_server-0.4.3.dist-info/WHEEL
openfund_server-0.4.3.dist-info/entry_points.txt
openfund_server-0.4.3.dist-info/RECORD
