Metadata-Version: 2.1
Name: openfund-server
Version: 0.4.3
Summary: FastAPI struct
Author: yang99love
Author-email: yang99love@hotmail.com
Requires-Python: >=3.11,<4.0
Classifier: Programming Language :: Python :: 3
Classifier: Programming Language :: Python :: 3.11
Classifier: Programming Language :: Python :: 3.12
Classifier: Programming Language :: Python :: 3.13
Requires-Dist: aiomysql (>=0.2.0,<0.3.0)
Requires-Dist: alembic (>=1.13.1,<2.0.0)
Requires-Dist: apscheduler (>=3.11.0,<4.0.0)
Requires-Dist: binance-connector (>=3.9.0,<4.0.0)
Requires-Dist: binance-futures-connector (>=4.1.0,<5.0.0)
Requires-Dist: celery (>=5.3.6,<6.0.0)
Requires-Dist: click (>=8.1.7,<9.0.0)
Requires-Dist: coverage (>=7.4.0,<8.0.0)
Requires-Dist: cryptography (>=41.0.7,<42.0.0)
Requires-Dist: dependency-injector (>=4.41.0,<5.0.0)
Requires-Dist: email-validator (>=2.2.0,<3.0.0)
Requires-Dist: fastapi (>=0.109.0,<0.110.0)
Requires-Dist: fastapi-event (>=0.1.3,<0.2.0)
Requires-Dist: gunicorn (>=21.2.0,<22.0.0)
Requires-Dist: httpx (>=0.26.0,<0.27.0)
Requires-Dist: loguru (>=0.7.2,<0.8.0)
Requires-Dist: poetry (==1.8.4)
Requires-Dist: pydantic-settings (>=2.1.0,<3.0.0)
Requires-Dist: pyjwt (>=2.8.0,<3.0.0)
Requires-Dist: pymysql (>=1.1.0,<2.0.0)
Requires-Dist: pythondi (>=1.2.4,<2.0.0)
Requires-Dist: redis (>=5.0.1,<6.0.0)
Requires-Dist: sqlalchemy[asyncio] (>=2.0.25,<3.0.0)
Requires-Dist: ujson (>=5.9.0,<6.0.0)
Requires-Dist: uvicorn (>=0.25.0,<0.26.0)
